{
  "artifacts": [
    {
      "version": 1,
      "trained_at": "2026-06-25 14:45 UTC",
      "features": [
        "is_promo_period",
        "dow",
        "is_weekend",
        "month",
        "lag_1",
        "lag_3",
        "lag_7",
        "lag_14",
        "rolling_mean_7",
        "rolling_std_7"
      ],
      "training_rows": 1587,
      "metrics": {
        "mae": 32.86,
        "rmse": 41.83,
        "mape": 10.47
      },
      "status": "Healthy",
      "file": "model_v1.joblib"
    },
    {
      "version": 2,
      "trained_at": "2026-06-25 14:45 UTC",
      "features": [
        "is_promo_period",
        "dow",
        "is_weekend",
        "month",
        "lag_1",
        "lag_3",
        "lag_7",
        "lag_14",
        "rolling_mean_7",
        "rolling_std_7"
      ],
      "training_rows": 1587,
      "metrics": {
        "mae": 32.86,
        "rmse": 41.83,
        "mape": 10.47
      },
      "status": "Healthy",
      "file": "model_v2.joblib"
    },
    {
      "version": 3,
      "trained_at": "2026-06-25 16:37 UTC",
      "features": [
        "is_promo_period",
        "dow",
        "is_weekend",
        "month",
        "lag_1",
        "lag_3",
        "lag_7",
        "lag_14",
        "rolling_mean_7",
        "rolling_std_7"
      ],
      "training_rows": 1587,
      "metrics": {
        "mae": 32.86,
        "rmse": 41.83,
        "mape": 10.47
      },
      "status": "Healthy",
      "file": "model_v3.joblib"
    }
  ]
}